blueskysocial/__init__.py
blueskysocial/api_endpoints.py
blueskysocial/client.py
blueskysocial/errors.py
blueskysocial/handle_resolver.py
blueskysocial/image.py
blueskysocial/post.py
blueskysocial/post_attachment.py
blueskysocial/replies.py
blueskysocial/utils.py
blueskysocial/video.py
blueskysocial/webcard.py
blueskysocial/convos/__init__.py
blueskysocial/convos/convo.py
blueskysocial/convos/filters.py
blueskysocial/convos/message.py
blueskysocial/typedefs/__init__.py
blueskysocial/typedefs/_types.py
blueskysocial/typedefs/protocols.py
blueskysocial/typedefs/typecheck.py
blueskysocial-2.1.0.dist-info/LICENSE
blueskysocial-2.1.0.dist-info/METADATA
blueskysocial-2.1.0.dist-info/WHEEL
blueskysocial-2.1.0.dist-info/top_level.txt
blueskysocial-2.1.0.dist-info/RECORD
