Metadata-Version: 2.1
Name: blueskysocial
Version: 2.1.0
Summary: API for BlueSky social network
Home-page: https://github.com/dmoggles/blueskysocial
Author: Dmitry Mogilevsky
Author-email: dmitry.mogilevsky@gmail.com
License: MIT
Classifier: Development Status :: 3 - Alpha
Classifier: License :: OSI Approved :: MIT License
Classifier: Programming Language :: Python :: 3
Classifier: Programming Language :: Python :: 3.6
Classifier: Programming Language :: Python :: 3.7
Classifier: Programming Language :: Python :: 3.8
Classifier: Programming Language :: Python :: 3.9
Requires-Python: >=3.6
Provides-Extra: dev
License-File: LICENSE
